[
    {
        "type": "message",
        "user": "U045EMA87",
        "text": "!\ud0c0\ub85c",
        "ts": "1479052461.000103"
    },
    {
        "type": "message",
        "subtype": "file_share",
        "text": "<@U0KDL4448|iriya_bot> uploaded a file: <https:\/\/sparcs.slack.com\/files\/iriya_bot\/F32JR3NPQ\/tarot.png|george \ub2d8\uc758 \ud0c0\ub85c \uacb0\uacfc> and commented: \uccab \ubc88\uc9f8 \uce74\ub4dc: *Judgement* \uc758 *\uc5ed* \ubc29\ud5a5. *\uc7ac\uae30\ubd88\ub2a5, \ud6c4\ud68c.*\n\ub450 \ubc88\uc9f8 \uce74\ub4dc: *The Tower* \uc758 *\uc815* \ubc29\ud5a5. *\ud30c\uad34, \ud30c\uba78.*\n\uc138 \ubc88\uc9f8 \uce74\ub4dc: *The Chariot* \uc758 *\uc5ed* \ubc29\ud5a5. *\ud3ed\uc8fc, \uc88c\uc808.*\n",
        "file": {
            "id": "F32JR3NPQ",
            "created": 1479052464,
            "timestamp": 1479052464,
            "name": "tarot.png",
            "title": "george \ub2d8\uc758 \ud0c0\ub85c \uacb0\uacfc",
            "mimetype": "image\/png",
            "filetype": "png",
            "pretty_type": "PNG",
            "user": "U0KDL4448",
            "editable": false,
            "size": 1574455,
            "mode": "hosted",
            "is_external": false,
            "external_type": "",
            "is_public": true,
            "public_url_shared": false,
            "display_as_bot": false,
            "username": "",
            "url_private": "https:\/\/files.slack.com\/files-pri\/T024SHLFD-F32JR3NPQ\/tarot.png?t=xoxe-2162598523-109853422566-108502472001-018625f664",
            "url_private_download": "https:\/\/files.slack.com\/files-pri\/T024SHLFD-F32JR3NPQ\/download\/tarot.png?t=xoxe-2162598523-109853422566-108502472001-018625f664",
            "thumb_64": "https:\/\/files.slack.com\/files-tmb\/T024SHLFD-F32JR3NPQ-63d2becafa\/tarot_64.png?t=xoxe-2162598523-109853422566-108502472001-018625f664",
            "thumb_80": "https:\/\/files.slack.com\/files-tmb\/T024SHLFD-F32JR3NPQ-63d2becafa\/tarot_80.png?t=xoxe-2162598523-109853422566-108502472001-018625f664",
            "thumb_360": "https:\/\/files.slack.com\/files-tmb\/T024SHLFD-F32JR3NPQ-63d2becafa\/tarot_360.png?t=xoxe-2162598523-109853422566-108502472001-018625f664",
            "thumb_360_w": 360,
            "thumb_360_h": 188,
            "thumb_480": "https:\/\/files.slack.com\/files-tmb\/T024SHLFD-F32JR3NPQ-63d2becafa\/tarot_480.png?t=xoxe-2162598523-109853422566-108502472001-018625f664",
            "thumb_480_w": 480,
            "thumb_480_h": 250,
            "thumb_160": "https:\/\/files.slack.com\/files-tmb\/T024SHLFD-F32JR3NPQ-63d2becafa\/tarot_160.png?t=xoxe-2162598523-109853422566-108502472001-018625f664",
            "thumb_720": "https:\/\/files.slack.com\/files-tmb\/T024SHLFD-F32JR3NPQ-63d2becafa\/tarot_720.png?t=xoxe-2162598523-109853422566-108502472001-018625f664",
            "thumb_720_w": 720,
            "thumb_720_h": 376,
            "thumb_960": "https:\/\/files.slack.com\/files-tmb\/T024SHLFD-F32JR3NPQ-63d2becafa\/tarot_960.png?t=xoxe-2162598523-109853422566-108502472001-018625f664",
            "thumb_960_w": 960,
            "thumb_960_h": 501,
            "thumb_1024": "https:\/\/files.slack.com\/files-tmb\/T024SHLFD-F32JR3NPQ-63d2becafa\/tarot_1024.png?t=xoxe-2162598523-109853422566-108502472001-018625f664",
            "thumb_1024_w": 1024,
            "thumb_1024_h": 534,
            "image_exif_rotation": 1,
            "original_w": 1150,
            "original_h": 600,
            "permalink": "https:\/\/sparcs.slack.com\/files\/iriya_bot\/F32JR3NPQ\/tarot.png",
            "permalink_public": "https:\/\/slack-files.com\/T024SHLFD-F32JR3NPQ-b2972c9154",
            "channels": [
                "C0KH5SY9H"
            ],
            "groups": [],
            "ims": [],
            "comments_count": 1,
            "initial_comment": {
                "id": "Fc32JR3TQE",
                "created": 1479052464,
                "timestamp": 1479052464,
                "user": "U0KDL4448",
                "is_intro": true,
                "comment": "\uccab \ubc88\uc9f8 \uce74\ub4dc: *Judgement* \uc758 *\uc5ed* \ubc29\ud5a5. *\uc7ac\uae30\ubd88\ub2a5, \ud6c4\ud68c.*\n\ub450 \ubc88\uc9f8 \uce74\ub4dc: *The Tower* \uc758 *\uc815* \ubc29\ud5a5. *\ud30c\uad34, \ud30c\uba78.*\n\uc138 \ubc88\uc9f8 \uce74\ub4dc: *The Chariot* \uc758 *\uc5ed* \ubc29\ud5a5. *\ud3ed\uc8fc, \uc88c\uc808.*\n",
                "channel": ""
            }
        },
        "user": "U0KDL4448",
        "upload": true,
        "display_as_bot": false,
        "username": "<@U0KDL4448|iriya_bot>",
        "bot_id": null,
        "ts": "1479052467.000104"
    },
    {
        "type": "message",
        "user": "U024SNAD0",
        "text": "!\ud0c0\ub85c",
        "ts": "1479053433.000105"
    },
    {
        "type": "message",
        "subtype": "file_share",
        "text": "<@U0KDL4448|iriya_bot> uploaded a file: <https:\/\/sparcs.slack.com\/files\/iriya_bot\/F318H6ZJM\/tarot.png|elaborate \ub2d8\uc758 \ud0c0\ub85c \uacb0\uacfc> and commented: \uccab \ubc88\uc9f8 \uce74\ub4dc: *The Hierophant* \uc758 *\uc5ed* \ubc29\ud5a5. *\ud611\ub7c9, \ub098\ud0dc.*\n\ub450 \ubc88\uc9f8 \uce74\ub4dc: *Queen of Cups* . *\uc120\ub7c9\ud558\uace0 \uacf5\uc815\ud55c \uc5ec\uc131, \ud589\ubcf5, \uc9c0\ud61c.*\n\uc138 \ubc88\uc9f8 \uce74\ub4dc: *Five of Pentacles* . *\ubb3c\uc9c8\uc801\uc778 \ud2b8\ub7ec\ube14.*\n",
        "file": {
            "id": "F318H6ZJM",
            "created": 1479053435,
            "timestamp": 1479053435,
            "name": "tarot.png",
            "title": "elaborate \ub2d8\uc758 \ud0c0\ub85c \uacb0\uacfc",
            "mimetype": "image\/png",
            "filetype": "png",
            "pretty_type": "PNG",
            "user": "U0KDL4448",
            "editable": false,
            "size": 1650045,
            "mode": "hosted",
            "is_external": false,
            "external_type": "",
            "is_public": true,
            "public_url_shared": false,
            "display_as_bot": false,
            "username": "",
            "url_private": "https:\/\/files.slack.com\/files-pri\/T024SHLFD-F318H6ZJM\/tarot.png?t=xoxe-2162598523-109853422566-108502472001-018625f664",
            "url_private_download": "https:\/\/files.slack.com\/files-pri\/T024SHLFD-F318H6ZJM\/download\/tarot.png?t=xoxe-2162598523-109853422566-108502472001-018625f664",
            "thumb_64": "https:\/\/files.slack.com\/files-tmb\/T024SHLFD-F318H6ZJM-70a8fbb76d\/tarot_64.png?t=xoxe-2162598523-109853422566-108502472001-018625f664",
            "thumb_80": "https:\/\/files.slack.com\/files-tmb\/T024SHLFD-F318H6ZJM-70a8fbb76d\/tarot_80.png?t=xoxe-2162598523-109853422566-108502472001-018625f664",
            "thumb_360": "https:\/\/files.slack.com\/files-tmb\/T024SHLFD-F318H6ZJM-70a8fbb76d\/tarot_360.png?t=xoxe-2162598523-109853422566-108502472001-018625f664",
            "thumb_360_w": 360,
            "thumb_360_h": 188,
            "thumb_480": "https:\/\/files.slack.com\/files-tmb\/T024SHLFD-F318H6ZJM-70a8fbb76d\/tarot_480.png?t=xoxe-2162598523-109853422566-108502472001-018625f664",
            "thumb_480_w": 480,
            "thumb_480_h": 250,
            "thumb_160": "https:\/\/files.slack.com\/files-tmb\/T024SHLFD-F318H6ZJM-70a8fbb76d\/tarot_160.png?t=xoxe-2162598523-109853422566-108502472001-018625f664",
            "thumb_720": "https:\/\/files.slack.com\/files-tmb\/T024SHLFD-F318H6ZJM-70a8fbb76d\/tarot_720.png?t=xoxe-2162598523-109853422566-108502472001-018625f664",
            "thumb_720_w": 720,
            "thumb_720_h": 376,
            "thumb_960": "https:\/\/files.slack.com\/files-tmb\/T024SHLFD-F318H6ZJM-70a8fbb76d\/tarot_960.png?t=xoxe-2162598523-109853422566-108502472001-018625f664",
            "thumb_960_w": 960,
            "thumb_960_h": 501,
            "thumb_1024": "https:\/\/files.slack.com\/files-tmb\/T024SHLFD-F318H6ZJM-70a8fbb76d\/tarot_1024.png?t=xoxe-2162598523-109853422566-108502472001-018625f664",
            "thumb_1024_w": 1024,
            "thumb_1024_h": 534,
            "image_exif_rotation": 1,
            "original_w": 1150,
            "original_h": 600,
            "permalink": "https:\/\/sparcs.slack.com\/files\/iriya_bot\/F318H6ZJM\/tarot.png",
            "permalink_public": "https:\/\/slack-files.com\/T024SHLFD-F318H6ZJM-a3f8abd5d2",
            "channels": [
                "C0KH5SY9H"
            ],
            "groups": [],
            "ims": [],
            "comments_count": 1,
            "initial_comment": {
                "id": "Fc317KR2U8",
                "created": 1479053435,
                "timestamp": 1479053435,
                "user": "U0KDL4448",
                "is_intro": true,
                "comment": "\uccab \ubc88\uc9f8 \uce74\ub4dc: *The Hierophant* \uc758 *\uc5ed* \ubc29\ud5a5. *\ud611\ub7c9, \ub098\ud0dc.*\n\ub450 \ubc88\uc9f8 \uce74\ub4dc: *Queen of Cups* . *\uc120\ub7c9\ud558\uace0 \uacf5\uc815\ud55c \uc5ec\uc131, \ud589\ubcf5, \uc9c0\ud61c.*\n\uc138 \ubc88\uc9f8 \uce74\ub4dc: *Five of Pentacles* . *\ubb3c\uc9c8\uc801\uc778 \ud2b8\ub7ec\ube14.*\n",
                "channel": ""
            }
        },
        "user": "U0KDL4448",
        "upload": true,
        "display_as_bot": false,
        "username": "<@U0KDL4448|iriya_bot>",
        "bot_id": null,
        "ts": "1479053439.000106"
    },
    {
        "type": "message",
        "user": "U02F86M4W",
        "text": "!\ud0c0\ub85c",
        "ts": "1479058069.000107"
    },
    {
        "type": "message",
        "subtype": "file_share",
        "text": "<@U0KDL4448|iriya_bot> uploaded a file: <https:\/\/sparcs.slack.com\/files\/iriya_bot\/F31SM4DSP\/tarot.png|chocho \ub2d8\uc758 \ud0c0\ub85c \uacb0\uacfc> and commented: \uccab \ubc88\uc9f8 \uce74\ub4dc: *The Chariot* \uc758 *\uc5ed* \ubc29\ud5a5. *\ud3ed\uc8fc, \uc88c\uc808.*\n\ub450 \ubc88\uc9f8 \uce74\ub4dc: *Five of Pentacles* . *\ubb3c\uc9c8\uc801\uc778 \ud2b8\ub7ec\ube14.*\n\uc138 \ubc88\uc9f8 \uce74\ub4dc: *Ten of Wands* . *\uc5b5\uc555, \ub108\ubb34 \ub9ce\uc740 \uc7ac\uc0b0.*\n",
        "file": {
            "id": "F31SM4DSP",
            "created": 1479058072,
            "timestamp": 1479058072,
            "name": "tarot.png",
            "title": "chocho \ub2d8\uc758 \ud0c0\ub85c \uacb0\uacfc",
            "mimetype": "image\/png",
            "filetype": "png",
            "pretty_type": "PNG",
            "user": "U0KDL4448",
            "editable": false,
            "size": 1595066,
            "mode": "hosted",
            "is_external": false,
            "external_type": "",
            "is_public": true,
            "public_url_shared": false,
            "display_as_bot": false,
            "username": "",
            "url_private": "https:\/\/files.slack.com\/files-pri\/T024SHLFD-F31SM4DSP\/tarot.png?t=xoxe-2162598523-109853422566-108502472001-018625f664",
            "url_private_download": "https:\/\/files.slack.com\/files-pri\/T024SHLFD-F31SM4DSP\/download\/tarot.png?t=xoxe-2162598523-109853422566-108502472001-018625f664",
            "thumb_64": "https:\/\/files.slack.com\/files-tmb\/T024SHLFD-F31SM4DSP-9094dd3403\/tarot_64.png?t=xoxe-2162598523-109853422566-108502472001-018625f664",
            "thumb_80": "https:\/\/files.slack.com\/files-tmb\/T024SHLFD-F31SM4DSP-9094dd3403\/tarot_80.png?t=xoxe-2162598523-109853422566-108502472001-018625f664",
            "thumb_360": "https:\/\/files.slack.com\/files-tmb\/T024SHLFD-F31SM4DSP-9094dd3403\/tarot_360.png?t=xoxe-2162598523-109853422566-108502472001-018625f664",
            "thumb_360_w": 360,
            "thumb_360_h": 188,
            "thumb_480": "https:\/\/files.slack.com\/files-tmb\/T024SHLFD-F31SM4DSP-9094dd3403\/tarot_480.png?t=xoxe-2162598523-109853422566-108502472001-018625f664",
            "thumb_480_w": 480,
            "thumb_480_h": 250,
            "thumb_160": "https:\/\/files.slack.com\/files-tmb\/T024SHLFD-F31SM4DSP-9094dd3403\/tarot_160.png?t=xoxe-2162598523-109853422566-108502472001-018625f664",
            "thumb_720": "https:\/\/files.slack.com\/files-tmb\/T024SHLFD-F31SM4DSP-9094dd3403\/tarot_720.png?t=xoxe-2162598523-109853422566-108502472001-018625f664",
            "thumb_720_w": 720,
            "thumb_720_h": 376,
            "thumb_960": "https:\/\/files.slack.com\/files-tmb\/T024SHLFD-F31SM4DSP-9094dd3403\/tarot_960.png?t=xoxe-2162598523-109853422566-108502472001-018625f664",
            "thumb_960_w": 960,
            "thumb_960_h": 501,
            "thumb_1024": "https:\/\/files.slack.com\/files-tmb\/T024SHLFD-F31SM4DSP-9094dd3403\/tarot_1024.png?t=xoxe-2162598523-109853422566-108502472001-018625f664",
            "thumb_1024_w": 1024,
            "thumb_1024_h": 534,
            "image_exif_rotation": 1,
            "original_w": 1150,
            "original_h": 600,
            "permalink": "https:\/\/sparcs.slack.com\/files\/iriya_bot\/F31SM4DSP\/tarot.png",
            "permalink_public": "https:\/\/slack-files.com\/T024SHLFD-F31SM4DSP-c3787b5724",
            "channels": [
                "C0KH5SY9H"
            ],
            "groups": [],
            "ims": [],
            "comments_count": 1,
            "initial_comment": {
                "id": "Fc32KDFS4X",
                "created": 1479058072,
                "timestamp": 1479058072,
                "user": "U0KDL4448",
                "is_intro": true,
                "comment": "\uccab \ubc88\uc9f8 \uce74\ub4dc: *The Chariot* \uc758 *\uc5ed* \ubc29\ud5a5. *\ud3ed\uc8fc, \uc88c\uc808.*\n\ub450 \ubc88\uc9f8 \uce74\ub4dc: *Five of Pentacles* . *\ubb3c\uc9c8\uc801\uc778 \ud2b8\ub7ec\ube14.*\n\uc138 \ubc88\uc9f8 \uce74\ub4dc: *Ten of Wands* . *\uc5b5\uc555, \ub108\ubb34 \ub9ce\uc740 \uc7ac\uc0b0.*\n",
                "channel": ""
            }
        },
        "user": "U0KDL4448",
        "upload": true,
        "display_as_bot": false,
        "username": "<@U0KDL4448|iriya_bot>",
        "bot_id": null,
        "ts": "1479058075.000108"
    },
    {
        "type": "message",
        "user": "U0V6MLCAH",
        "text": "!\ud0c0\ub85c",
        "ts": "1479070239.000109"
    },
    {
        "type": "message",
        "subtype": "file_share",
        "text": "<@U0KDL4448|iriya_bot> uploaded a file: <https:\/\/sparcs.slack.com\/files\/iriya_bot\/F319J4ML1\/tarot.png|hou \ub2d8\uc758 \ud0c0\ub85c \uacb0\uacfc> and commented: \uccab \ubc88\uc9f8 \uce74\ub4dc: *Page of Wands* . *\uc80a\uc740 \ub0a8\uc131, \ucda9\uc2e4, \uc678\uad50\uc0ac\uc808, \uc6b0\ud3b8.*\n\ub450 \ubc88\uc9f8 \uce74\ub4dc: *Seven of Pentacles* . *\uae08\uc804, \uc0ac\uc5c5, \uad50\uc5ed.*\n\uc138 \ubc88\uc9f8 \uce74\ub4dc: *The High Priestess* \uc758 *\uc5ed* \ubc29\ud5a5. *\uc794\ud639, \ubb34\ub840\ud568.*\n",
        "file": {
            "id": "F319J4ML1",
            "created": 1479070241,
            "timestamp": 1479070241,
            "name": "tarot.png",
            "title": "hou \ub2d8\uc758 \ud0c0\ub85c \uacb0\uacfc",
            "mimetype": "image\/png",
            "filetype": "png",
            "pretty_type": "PNG",
            "user": "U0KDL4448",
            "editable": false,
            "size": 1497115,
            "mode": "hosted",
            "is_external": false,
            "external_type": "",
            "is_public": true,
            "public_url_shared": false,
            "display_as_bot": false,
            "username": "",
            "url_private": "https:\/\/files.slack.com\/files-pri\/T024SHLFD-F319J4ML1\/tarot.png?t=xoxe-2162598523-109853422566-108502472001-018625f664",
            "url_private_download": "https:\/\/files.slack.com\/files-pri\/T024SHLFD-F319J4ML1\/download\/tarot.png?t=xoxe-2162598523-109853422566-108502472001-018625f664",
            "thumb_64": "https:\/\/files.slack.com\/files-tmb\/T024SHLFD-F319J4ML1-d33789aa84\/tarot_64.png?t=xoxe-2162598523-109853422566-108502472001-018625f664",
            "thumb_80": "https:\/\/files.slack.com\/files-tmb\/T024SHLFD-F319J4ML1-d33789aa84\/tarot_80.png?t=xoxe-2162598523-109853422566-108502472001-018625f664",
            "thumb_360": "https:\/\/files.slack.com\/files-tmb\/T024SHLFD-F319J4ML1-d33789aa84\/tarot_360.png?t=xoxe-2162598523-109853422566-108502472001-018625f664",
            "thumb_360_w": 360,
            "thumb_360_h": 188,
            "thumb_480": "https:\/\/files.slack.com\/files-tmb\/T024SHLFD-F319J4ML1-d33789aa84\/tarot_480.png?t=xoxe-2162598523-109853422566-108502472001-018625f664",
            "thumb_480_w": 480,
            "thumb_480_h": 250,
            "thumb_160": "https:\/\/files.slack.com\/files-tmb\/T024SHLFD-F319J4ML1-d33789aa84\/tarot_160.png?t=xoxe-2162598523-109853422566-108502472001-018625f664",
            "thumb_720": "https:\/\/files.slack.com\/files-tmb\/T024SHLFD-F319J4ML1-d33789aa84\/tarot_720.png?t=xoxe-2162598523-109853422566-108502472001-018625f664",
            "thumb_720_w": 720,
            "thumb_720_h": 376,
            "thumb_960": "https:\/\/files.slack.com\/files-tmb\/T024SHLFD-F319J4ML1-d33789aa84\/tarot_960.png?t=xoxe-2162598523-109853422566-108502472001-018625f664",
            "thumb_960_w": 960,
            "thumb_960_h": 501,
            "thumb_1024": "https:\/\/files.slack.com\/files-tmb\/T024SHLFD-F319J4ML1-d33789aa84\/tarot_1024.png?t=xoxe-2162598523-109853422566-108502472001-018625f664",
            "thumb_1024_w": 1024,
            "thumb_1024_h": 534,
            "image_exif_rotation": 1,
            "original_w": 1150,
            "original_h": 600,
            "permalink": "https:\/\/sparcs.slack.com\/files\/iriya_bot\/F319J4ML1\/tarot.png",
            "permalink_public": "https:\/\/slack-files.com\/T024SHLFD-F319J4ML1-15b59592d0",
            "channels": [
                "C0KH5SY9H"
            ],
            "groups": [],
            "ims": [],
            "comments_count": 1,
            "initial_comment": {
                "id": "Fc31TD2ELB",
                "created": 1479070241,
                "timestamp": 1479070241,
                "user": "U0KDL4448",
                "is_intro": true,
                "comment": "\uccab \ubc88\uc9f8 \uce74\ub4dc: *Page of Wands* . *\uc80a\uc740 \ub0a8\uc131, \ucda9\uc2e4, \uc678\uad50\uc0ac\uc808, \uc6b0\ud3b8.*\n\ub450 \ubc88\uc9f8 \uce74\ub4dc: *Seven of Pentacles* . *\uae08\uc804, \uc0ac\uc5c5, \uad50\uc5ed.*\n\uc138 \ubc88\uc9f8 \uce74\ub4dc: *The High Priestess* \uc758 *\uc5ed* \ubc29\ud5a5. *\uc794\ud639, \ubb34\ub840\ud568.*\n",
                "channel": ""
            }
        },
        "user": "U0KDL4448",
        "upload": true,
        "display_as_bot": false,
        "username": "<@U0KDL4448|iriya_bot>",
        "bot_id": null,
        "ts": "1479070245.000110"
    },
    {
        "type": "message",
        "user": "U024SKNH9",
        "text": "!\ud0c0\ub85c",
        "ts": "1479083065.000111"
    },
    {
        "type": "message",
        "subtype": "file_share",
        "text": "<@U0KDL4448|iriya_bot> uploaded a file: <https:\/\/sparcs.slack.com\/files\/iriya_bot\/F319E8QJU\/tarot.png|whitegold \ub2d8\uc758 \ud0c0\ub85c \uacb0\uacfc> and commented: \uccab \ubc88\uc9f8 \uce74\ub4dc: *King of Wands* . *\uc2dc\uace8\uc758 \ub0a8\uc131, \uc815\uc9c1, \uc591\uc2ec\uc801.*\n\ub450 \ubc88\uc9f8 \uce74\ub4dc: *Three of Cups* . *\ud48d\uc871\ud568, \ud589\ubcf5, \uc131\ucde8, \uce58\uc720.*\n\uc138 \ubc88\uc9f8 \uce74\ub4dc: *Seven of Pentacles* . *\uae08\uc804, \uc0ac\uc5c5, \uad50\uc5ed.*\n",
        "file": {
            "id": "F319E8QJU",
            "created": 1479083067,
            "timestamp": 1479083067,
            "name": "tarot.png",
            "title": "whitegold \ub2d8\uc758 \ud0c0\ub85c \uacb0\uacfc",
            "mimetype": "image\/png",
            "filetype": "png",
            "pretty_type": "PNG",
            "user": "U0KDL4448",
            "editable": false,
            "size": 1562827,
            "mode": "hosted",
            "is_external": false,
            "external_type": "",
            "is_public": true,
            "public_url_shared": false,
            "display_as_bot": false,
            "username": "",
            "url_private": "https:\/\/files.slack.com\/files-pri\/T024SHLFD-F319E8QJU\/tarot.png?t=xoxe-2162598523-109853422566-108502472001-018625f664",
            "url_private_download": "https:\/\/files.slack.com\/files-pri\/T024SHLFD-F319E8QJU\/download\/tarot.png?t=xoxe-2162598523-109853422566-108502472001-018625f664",
            "thumb_64": "https:\/\/files.slack.com\/files-tmb\/T024SHLFD-F319E8QJU-50f7bade9b\/tarot_64.png?t=xoxe-2162598523-109853422566-108502472001-018625f664",
            "thumb_80": "https:\/\/files.slack.com\/files-tmb\/T024SHLFD-F319E8QJU-50f7bade9b\/tarot_80.png?t=xoxe-2162598523-109853422566-108502472001-018625f664",
            "thumb_360": "https:\/\/files.slack.com\/files-tmb\/T024SHLFD-F319E8QJU-50f7bade9b\/tarot_360.png?t=xoxe-2162598523-109853422566-108502472001-018625f664",
            "thumb_360_w": 360,
            "thumb_360_h": 188,
            "thumb_480": "https:\/\/files.slack.com\/files-tmb\/T024SHLFD-F319E8QJU-50f7bade9b\/tarot_480.png?t=xoxe-2162598523-109853422566-108502472001-018625f664",
            "thumb_480_w": 480,
            "thumb_480_h": 250,
            "thumb_160": "https:\/\/files.slack.com\/files-tmb\/T024SHLFD-F319E8QJU-50f7bade9b\/tarot_160.png?t=xoxe-2162598523-109853422566-108502472001-018625f664",
            "thumb_720": "https:\/\/files.slack.com\/files-tmb\/T024SHLFD-F319E8QJU-50f7bade9b\/tarot_720.png?t=xoxe-2162598523-109853422566-108502472001-018625f664",
            "thumb_720_w": 720,
            "thumb_720_h": 376,
            "thumb_960": "https:\/\/files.slack.com\/files-tmb\/T024SHLFD-F319E8QJU-50f7bade9b\/tarot_960.png?t=xoxe-2162598523-109853422566-108502472001-018625f664",
            "thumb_960_w": 960,
            "thumb_960_h": 501,
            "thumb_1024": "https:\/\/files.slack.com\/files-tmb\/T024SHLFD-F319E8QJU-50f7bade9b\/tarot_1024.png?t=xoxe-2162598523-109853422566-108502472001-018625f664",
            "thumb_1024_w": 1024,
            "thumb_1024_h": 534,
            "image_exif_rotation": 1,
            "original_w": 1150,
            "original_h": 600,
            "permalink": "https:\/\/sparcs.slack.com\/files\/iriya_bot\/F319E8QJU\/tarot.png",
            "permalink_public": "https:\/\/slack-files.com\/T024SHLFD-F319E8QJU-93c1412b45",
            "channels": [
                "C0KH5SY9H"
            ],
            "groups": [],
            "ims": [],
            "comments_count": 1,
            "initial_comment": {
                "id": "Fc32LMC0P8",
                "created": 1479083067,
                "timestamp": 1479083067,
                "user": "U0KDL4448",
                "is_intro": true,
                "comment": "\uccab \ubc88\uc9f8 \uce74\ub4dc: *King of Wands* . *\uc2dc\uace8\uc758 \ub0a8\uc131, \uc815\uc9c1, \uc591\uc2ec\uc801.*\n\ub450 \ubc88\uc9f8 \uce74\ub4dc: *Three of Cups* . *\ud48d\uc871\ud568, \ud589\ubcf5, \uc131\ucde8, \uce58\uc720.*\n\uc138 \ubc88\uc9f8 \uce74\ub4dc: *Seven of Pentacles* . *\uae08\uc804, \uc0ac\uc5c5, \uad50\uc5ed.*\n",
                "channel": ""
            }
        },
        "user": "U0KDL4448",
        "upload": true,
        "display_as_bot": false,
        "username": "<@U0KDL4448|iriya_bot>",
        "bot_id": null,
        "ts": "1479083071.000112"
    },
    {
        "type": "message",
        "user": "U024U2P7Y",
        "text": "!\ud0c0\ub85c",
        "ts": "1479102158.000113"
    },
    {
        "type": "message",
        "subtype": "file_share",
        "text": "<@U0KDL4448|iriya_bot> uploaded a file: <https:\/\/sparcs.slack.com\/files\/iriya_bot\/F320C5DS7\/tarot.png|suckzo_o \ub2d8\uc758 \ud0c0\ub85c \uacb0\uacfc> and commented: \uccab \ubc88\uc9f8 \uce74\ub4dc: *Nine of Swords* . *\uc2e4\ub9dd, \ud658\uba78.*\n\ub450 \ubc88\uc9f8 \uce74\ub4dc: *The World* \uc758 *\uc815* \ubc29\ud5a5. *\uc644\uc131, \uc644\uc804.*\n\uc138 \ubc88\uc9f8 \uce74\ub4dc: *Eight of Cups* . *\uc131\uacf5\uc758 \ubc29\uce58, \uacb8\uc190.*\n",
        "file": {
            "id": "F320C5DS7",
            "created": 1479102161,
            "timestamp": 1479102161,
            "name": "tarot.png",
            "title": "suckzo_o \ub2d8\uc758 \ud0c0\ub85c \uacb0\uacfc",
            "mimetype": "image\/png",
            "filetype": "png",
            "pretty_type": "PNG",
            "user": "U0KDL4448",
            "editable": false,
            "size": 1544341,
            "mode": "hosted",
            "is_external": false,
            "external_type": "",
            "is_public": true,
            "public_url_shared": false,
            "display_as_bot": false,
            "username": "",
            "url_private": "https:\/\/files.slack.com\/files-pri\/T024SHLFD-F320C5DS7\/tarot.png?t=xoxe-2162598523-109853422566-108502472001-018625f664",
            "url_private_download": "https:\/\/files.slack.com\/files-pri\/T024SHLFD-F320C5DS7\/download\/tarot.png?t=xoxe-2162598523-109853422566-108502472001-018625f664",
            "thumb_64": "https:\/\/files.slack.com\/files-tmb\/T024SHLFD-F320C5DS7-5f3c279032\/tarot_64.png?t=xoxe-2162598523-109853422566-108502472001-018625f664",
            "thumb_80": "https:\/\/files.slack.com\/files-tmb\/T024SHLFD-F320C5DS7-5f3c279032\/tarot_80.png?t=xoxe-2162598523-109853422566-108502472001-018625f664",
            "thumb_360": "https:\/\/files.slack.com\/files-tmb\/T024SHLFD-F320C5DS7-5f3c279032\/tarot_360.png?t=xoxe-2162598523-109853422566-108502472001-018625f664",
            "thumb_360_w": 360,
            "thumb_360_h": 188,
            "thumb_480": "https:\/\/files.slack.com\/files-tmb\/T024SHLFD-F320C5DS7-5f3c279032\/tarot_480.png?t=xoxe-2162598523-109853422566-108502472001-018625f664",
            "thumb_480_w": 480,
            "thumb_480_h": 250,
            "thumb_160": "https:\/\/files.slack.com\/files-tmb\/T024SHLFD-F320C5DS7-5f3c279032\/tarot_160.png?t=xoxe-2162598523-109853422566-108502472001-018625f664",
            "thumb_720": "https:\/\/files.slack.com\/files-tmb\/T024SHLFD-F320C5DS7-5f3c279032\/tarot_720.png?t=xoxe-2162598523-109853422566-108502472001-018625f664",
            "thumb_720_w": 720,
            "thumb_720_h": 376,
            "thumb_960": "https:\/\/files.slack.com\/files-tmb\/T024SHLFD-F320C5DS7-5f3c279032\/tarot_960.png?t=xoxe-2162598523-109853422566-108502472001-018625f664",
            "thumb_960_w": 960,
            "thumb_960_h": 501,
            "thumb_1024": "https:\/\/files.slack.com\/files-tmb\/T024SHLFD-F320C5DS7-5f3c279032\/tarot_1024.png?t=xoxe-2162598523-109853422566-108502472001-018625f664",
            "thumb_1024_w": 1024,
            "thumb_1024_h": 534,
            "image_exif_rotation": 1,
            "original_w": 1150,
            "original_h": 600,
            "permalink": "https:\/\/sparcs.slack.com\/files\/iriya_bot\/F320C5DS7\/tarot.png",
            "permalink_public": "https:\/\/slack-files.com\/T024SHLFD-F320C5DS7-f9f26f713d",
            "channels": [
                "C0KH5SY9H"
            ],
            "groups": [],
            "ims": [],
            "comments_count": 1,
            "initial_comment": {
                "id": "Fc324X9X0V",
                "created": 1479102161,
                "timestamp": 1479102161,
                "user": "U0KDL4448",
                "is_intro": true,
                "comment": "\uccab \ubc88\uc9f8 \uce74\ub4dc: *Nine of Swords* . *\uc2e4\ub9dd, \ud658\uba78.*\n\ub450 \ubc88\uc9f8 \uce74\ub4dc: *The World* \uc758 *\uc815* \ubc29\ud5a5. *\uc644\uc131, \uc644\uc804.*\n\uc138 \ubc88\uc9f8 \uce74\ub4dc: *Eight of Cups* . *\uc131\uacf5\uc758 \ubc29\uce58, \uacb8\uc190.*\n",
                "channel": ""
            }
        },
        "user": "U0KDL4448",
        "upload": true,
        "display_as_bot": false,
        "username": "<@U0KDL4448|iriya_bot>",
        "bot_id": null,
        "ts": "1479102164.000114"
    },
    {
        "type": "message",
        "user": "U04JG832D",
        "text": "!\ud0c0\ub85c",
        "ts": "1479104601.000115"
    },
    {
        "type": "message",
        "subtype": "file_share",
        "text": "<@U0KDL4448|iriya_bot> uploaded a file: <https:\/\/sparcs.slack.com\/files\/iriya_bot\/F31C3P91P\/tarot.png|jara \ub2d8\uc758 \ud0c0\ub85c \uacb0\uacfc> and commented: \uccab \ubc88\uc9f8 \uce74\ub4dc: *Queen of Wands* . *\uc2dc\uace8\uc758 \uc5ec\uc131, \uce5c\uc219\ud55c \uc815\uc801, \uc874\uacbd.*\n\ub450 \ubc88\uc9f8 \uce74\ub4dc: *The Empress* \uc758 *\uc815* \ubc29\ud5a5. *\ud48d\uc591, \ubaa8\uc131.*\n\uc138 \ubc88\uc9f8 \uce74\ub4dc: *Four of Wands* . *\uc791\uc5c5\uc758 \uc644\uc131, \ud734\uc2dd, \ud3c9\ud654.*\n",
        "file": {
            "id": "F31C3P91P",
            "created": 1479104603,
            "timestamp": 1479104603,
            "name": "tarot.png",
            "title": "jara \ub2d8\uc758 \ud0c0\ub85c \uacb0\uacfc",
            "mimetype": "image\/png",
            "filetype": "png",
            "pretty_type": "PNG",
            "user": "U0KDL4448",
            "editable": false,
            "size": 1490363,
            "mode": "hosted",
            "is_external": false,
            "external_type": "",
            "is_public": true,
            "public_url_shared": false,
            "display_as_bot": false,
            "username": "",
            "url_private": "https:\/\/files.slack.com\/files-pri\/T024SHLFD-F31C3P91P\/tarot.png?t=xoxe-2162598523-109853422566-108502472001-018625f664",
            "url_private_download": "https:\/\/files.slack.com\/files-pri\/T024SHLFD-F31C3P91P\/download\/tarot.png?t=xoxe-2162598523-109853422566-108502472001-018625f664",
            "thumb_64": "https:\/\/files.slack.com\/files-tmb\/T024SHLFD-F31C3P91P-8e43b52af9\/tarot_64.png?t=xoxe-2162598523-109853422566-108502472001-018625f664",
            "thumb_80": "https:\/\/files.slack.com\/files-tmb\/T024SHLFD-F31C3P91P-8e43b52af9\/tarot_80.png?t=xoxe-2162598523-109853422566-108502472001-018625f664",
            "thumb_360": "https:\/\/files.slack.com\/files-tmb\/T024SHLFD-F31C3P91P-8e43b52af9\/tarot_360.png?t=xoxe-2162598523-109853422566-108502472001-018625f664",
            "thumb_360_w": 360,
            "thumb_360_h": 188,
            "thumb_480": "https:\/\/files.slack.com\/files-tmb\/T024SHLFD-F31C3P91P-8e43b52af9\/tarot_480.png?t=xoxe-2162598523-109853422566-108502472001-018625f664",
            "thumb_480_w": 480,
            "thumb_480_h": 250,
            "thumb_160": "https:\/\/files.slack.com\/files-tmb\/T024SHLFD-F31C3P91P-8e43b52af9\/tarot_160.png?t=xoxe-2162598523-109853422566-108502472001-018625f664",
            "thumb_720": "https:\/\/files.slack.com\/files-tmb\/T024SHLFD-F31C3P91P-8e43b52af9\/tarot_720.png?t=xoxe-2162598523-109853422566-108502472001-018625f664",
            "thumb_720_w": 720,
            "thumb_720_h": 376,
            "thumb_960": "https:\/\/files.slack.com\/files-tmb\/T024SHLFD-F31C3P91P-8e43b52af9\/tarot_960.png?t=xoxe-2162598523-109853422566-108502472001-018625f664",
            "thumb_960_w": 960,
            "thumb_960_h": 501,
            "thumb_1024": "https:\/\/files.slack.com\/files-tmb\/T024SHLFD-F31C3P91P-8e43b52af9\/tarot_1024.png?t=xoxe-2162598523-109853422566-108502472001-018625f664",
            "thumb_1024_w": 1024,
            "thumb_1024_h": 534,
            "image_exif_rotation": 1,
            "original_w": 1150,
            "original_h": 600,
            "permalink": "https:\/\/sparcs.slack.com\/files\/iriya_bot\/F31C3P91P\/tarot.png",
            "permalink_public": "https:\/\/slack-files.com\/T024SHLFD-F31C3P91P-99919c2d17",
            "channels": [
                "C0KH5SY9H"
            ],
            "groups": [],
            "ims": [],
            "comments_count": 1,
            "initial_comment": {
                "id": "Fc31B6F7C0",
                "created": 1479104603,
                "timestamp": 1479104603,
                "user": "U0KDL4448",
                "is_intro": true,
                "comment": "\uccab \ubc88\uc9f8 \uce74\ub4dc: *Queen of Wands* . *\uc2dc\uace8\uc758 \uc5ec\uc131, \uce5c\uc219\ud55c \uc815\uc801, \uc874\uacbd.*\n\ub450 \ubc88\uc9f8 \uce74\ub4dc: *The Empress* \uc758 *\uc815* \ubc29\ud5a5. *\ud48d\uc591, \ubaa8\uc131.*\n\uc138 \ubc88\uc9f8 \uce74\ub4dc: *Four of Wands* . *\uc791\uc5c5\uc758 \uc644\uc131, \ud734\uc2dd, \ud3c9\ud654.*\n",
                "channel": ""
            }
        },
        "user": "U0KDL4448",
        "upload": true,
        "display_as_bot": false,
        "username": "<@U0KDL4448|iriya_bot>",
        "bot_id": null,
        "ts": "1479104607.000116"
    }
]