[
    {
        "type": "message",
        "user": "U02HV8AGZ",
        "text": "\uc2a4\ub9c8\ud2b8\ud3f0\uc5d0\uc11c \uc778\ud130\ub137\uc744 \ud1b5\ud558\uc5ec \ub77c\uc988\ubca0\ub9ac \ud30c\uc774\uc5d0 \uc811\uc18d\ud558\uc5ec \uba85\ub839\uc744 \ub0b4\ub9ac\uba74\n\ub77c\uc988\ubca0\ub9ac\ud30c\uc774\ub294 IR\uc744 \uc774\uc6a9\ud558\uc5ec \uc5d0\uc5b4\ucee8\uc744 \uc870\uc791\ud558\uba74 \ub420\uac83\uac19\uc544\uc694.",
        "ts": "1410937277.000015"
    },
    {
        "type": "message",
        "user": "U024SJ4KZ",
        "text": "\ub135\ub135 \uc774\ub530 \uc218\uc5c5 \ub2e4 \ub05d\ub098\uace0 \uc77d\uc5b4\ubcfc\uac8c\uc694~",
        "ts": "1410937949.000016"
    }
]